Workbook

Sheet Supuestos
A1: Agente Facturas · Supuestos del modelo de costes
A2: Azul = dato que puede cambiar. Amarillo = el supuesto más importante: sustitúyalo por su dato real en cuanto lo tenga.
A3: Supuesto | B3: Valor | C3: Unidad | D3: Origen / nota
A4: Coste de IA por factura (una lectura) | B4: 0.1 | C4: USD | D4: Estimación de Ruben (≈10 céntimos). Medirla con /admin/uso-ia con un lote limpio.
A5: Factor de relecturas | B5: 1.1 | C5: x | D5: Supuesto: un 10 % de facturas se relee por confianza baja. Ajustar con el contador.
A6: Cambio USD → EUR | B6: 0.92 | C6: € por $ | D6: Supuesto: ajustar al cambio del día.
A7: IVA | B7: 0.21 | C7: % | D7: IVA general en España.
A8: Stripe: porcentaje por cobro | B8: 0.015 | C8: % | D8: Tarjetas del Espacio Económico Europeo (estándar). Tarjetas premium: 1,9 %. Fuente: Quipu (blog).
A9: Stripe Billing: porcentaje por suscripción | B9: 0.005 | C9: % | D9: 0,5 % de los pagos recurrentes. Fuente: Quipu (blog).
A10: Stripe: importe fijo por cobro | B10: 0.25 | C10: € | D10: 0,25 € por cobro. Fuente: Quipu (blog).
A11: Mensajería WhatsApp por factura | B11: 0 | C11: € | D11: Pendiente: WhatsApp aún no está activo. Rellenar con la tarifa vigente de Meta.
A12: Coste hora de un administrativo | B12: 18 | C12: €/h | D12: Supuesto (coste empresa aproximado). Sirve solo para el valor que recibe el cliente.
A13: Minutos por factura a mano | B13: 3 | C13: min | D13: Estimación de Ruben. Confirmar con la gestoría de prueba.
A14: Facturas al mes del cliente típico | B14: 200 | C14: facturas | D14: Supuesto. Sustituir por el dato de la gestoría de prueba.
A15: Objetivo de ingresos netos mensuales | B15: 2000 | C15: € | D15: Antes de impuestos y cuota de autónomos. Cámbielo a su objetivo.
A17: Tramos de precio propuestos (sin IVA, al mes)
A18: Tramo | B18: Hasta (facturas/mes) | C18: Precio (€/mes) | D18: Nota
A19: Tramo 1 | B19: 200 | C19: 49 | D19: Propuesta ajustada al coste de IA de 0,10 $ por factura (margen ≈50 % o más).
A20: Tramo 2 | B20: 1000 | C20: 249 | D20: Propuesta ajustada al coste de IA de 0,10 $ por factura (margen ≈50 % o más).
A21: Tramo 3 | B21: 3000 | C21: 599 | D21: Propuesta ajustada al coste de IA de 0,10 $ por factura (margen ≈50 % o más).
A22: Por encima del tramo 3 | B22: cada factura extra | C22: 0.2 | D22: € por factura adicional sobre el precio del tramo 3.
A24: Precio de lanzamiento | B24: 100 | C24: 29 | D24: Límite de facturas y precio de la promoción.
A26: Precio fijo de comparación 1 | C26: 49 | D26: Un plan único, sin tramos.
A27: Precio fijo de comparación 2 | C27: 100 | D27: Un plan único, sin tramos.

Sheet Fijos
A1: Costes fijos mensuales
A2: Producción = lo que costará con clientes de pago. Piloto = lo que cuesta hoy con la gestoría de prueba.
A3: Concepto | B3: Producción (USD/mes) | C3: Producción (€/mes) | D3: Piloto (€/mes) | E3: Qué incluye / fuente
A4: Servidor (Render) | B4: 7 | C4: =B4*Supuestos!$B$6 -> 6.44 | D4: 0 | E4: Plan de pago de 7 $ (menos de 1 CPU, 512 MB): no se duerme. El plan gratuito se duerme y por eso hoy usa cron. Fuente: render.com/pricing.
A5: Base de datos (Supabase Pro) | B5: 25 | C5: =B5*Supuestos!$B$6 -> 23 | D5: 0 | E5: Desde 25 $/mes: copias diarias 7 días, nunca se pausa. El plan gratuito no tiene copias automáticas y pausa tras 1 semana sin actividad. Fuente: supabase.com/docs/pricing.
A6: Correo de avisos (Resend) | B6: 0 | C6: =B6*Supuestos!$B$6 -> 0 | D6: 0 | E6: Gratis hasta 3.000 correos/mes y 100/día. Pro: 20 $/mes. Fuente: automationatlas.io (confirmar en resend.com).
A7: Dominio agentefacturas.es (€/año ÷ 12) | C7: =H7/12 -> 0.83333333 | D7: =H7/12 -> 0.83333333 | E7: Supuesto: ajustar con el precio real pagado en DonDominio (celda amarilla H7). | G7: €/año: | H7: 10
A8: Otros fijos (correo profesional, asesoría, seguros...) | C8: 0 | D8: 0 | E8: A rellenar. No incluye cuota de autónomos ni impuestos.
A9: TOTAL FIJOS | C9: =SUM(C4:C8) -> 30.273333 | D9: =SUM(D4:D8) -> 0.83333333

Sheet Escenarios
A1: Margen por cliente según su volumen de facturas
A2: Costes variables = IA + WhatsApp + comisión de Stripe. El margen es antes de los costes fijos, impuestos y de su tiempo.
A4: Facturas/mes | B4: Coste IA (€) | C4: WhatsApp (€) | D4: Precio del tramo (€, sin IVA) | E4: Stripe (€) | F4: Margen del tramo (€) | G4: Margen del tramo (%) | H4: Margen con plan fijo 1 (€) | I4: Margen con plan fijo 2 (€) | J4: Ahorro del cliente (€/mes) | K4: Precio como % del ahorro
A5: 50 | B5: =A5*Supuestos!$B$5*Supuestos!$B$4*Supuestos!$B$6 -> 5.06 | C5: =A5*Supuestos!$B$11 -> 0 | D5: =IF(A5<=Supuestos!$B$19,Supuestos!$C$19,IF(A5<=Supuestos!$B$20,Supuestos!$C$20,IF(A5<=Supuestos!$B$21,Supuestos!$C$21,Supuestos!$C$21+(A5-Supuestos!$B$21)*Supuestos!$C$22))) -> 49 | E5: =D5*(1+Supuestos!$B$7)*(Supuestos!$B$8+Supuestos!$B$9)+Supuestos!$B$10 -> 1.4358 | F5: =D5-B5-C5-E5 -> 42.5042 | G5: =IF(D5=0,0,F5/D5) -> 0.86743265 | H5: =Supuestos!$C$26-B5-C5-(Supuestos!$C$26*(1+Supuestos!$B$7)*(Supuestos!$B$8+Supuestos!$B$9)+Supuestos!$B$10) -> 42.5042 | I5: =Supuestos!$C$27-B5-C5-(Supuestos!$C$27*(1+Supuestos!$B$7)*(Supuestos!$B$8+Supuestos!$B$9)+Supuestos!$B$10) -> 92.27 | J5: =A5*Supuestos!$B$13/60*Supuestos!$B$12 -> 45 | K5: =IF(J5=0,0,D5/J5) -> 1.0888889
A6: 100 | B6: =A6*Supuestos!$B$5*Supuestos!$B$4*Supuestos!$B$6 -> 10.12 | C6: =A6*Supuestos!$B$11 -> 0 | D6: =IF(A6<=Supuestos!$B$19,Supuestos!$C$19,IF(A6<=Supuestos!$B$20,Supuestos!$C$20,IF(A6<=Supuestos!$B$21,Supuestos!$C$21,Supuestos!$C$21+(A6-Supuestos!$B$21)*Supuestos!$C$22))) -> 49 | E6: =D6*(1+Supuestos!$B$7)*(Supuestos!$B$8+Supuestos!$B$9)+Supuestos!$B$10 -> 1.4358 | F6: =D6-B6-C6-E6 -> 37.4442 | G6: =IF(D6=0,0,F6/D6) -> 0.76416735 | H6: =Supuestos!$C$26-B6-C6-(Supuestos!$C$26*(1+Supuestos!$B$7)*(Supuestos!$B$8+Supuestos!$B$9)+Supuestos!$B$10) -> 37.4442 | I6: =Supuestos!$C$27-B6-C6-(Supuestos!$C$27*(1+Supuestos!$B$7)*(Supuestos!$B$8+Supuestos!$B$9)+Supuestos!$B$10) -> 87.21 | J6: =A6*Supuestos!$B$13/60*Supuestos!$B$12 -> 90 | K6: =IF(J6=0,0,D6/J6) -> 0.54444444
A7: 200 | B7: =A7*Supuestos!$B$5*Supuestos!$B$4*Supuestos!$B$6 -> 20.24 | C7: =A7*Supuestos!$B$11 -> 0 | D7: =IF(A7<=Supuestos!$B$19,Supuestos!$C$19,IF(A7<=Supuestos!$B$20,Supuestos!$C$20,IF(A7<=Supuestos!$B$21,Supuestos!$C$21,Supuestos!$C$21+(A7-Supuestos!$B$21)*Supuestos!$C$22))) -> 49 | E7: =D7*(1+Supuestos!$B$7)*(Supuestos!$B$8+Supuestos!$B$9)+Supuestos!$B$10 -> 1.4358 | F7: =D7-B7-C7-E7 -> 27.3242 | G7: =IF(D7=0,0,F7/D7) -> 0.55763673 | H7: =Supuestos!$C$26-B7-C7-(Supuestos!$C$26*(1+Supuestos!$B$7)*(Supuestos!$B$8+Supuestos!$B$9)+Supuestos!$B$10) -> 27.3242 | I7: =Supuestos!$C$27-B7-C7-(Supuestos!$C$27*(1+Supuestos!$B$7)*(Supuestos!$B$8+Supuestos!$B$9)+Supuestos!$B$10) -> 77.09 | J7: =A7*Supuestos!$B$13/60*Supuestos!$B$12 -> 180 | K7: =IF(J7=0,0,D7/J7) -> 0.27222222
A8: 500 | B8: =A8*Supuestos!$B$5*Supuestos!$B$4*Supuestos!$B$6 -> 50.6 | C8: =A8*Supuestos!$B$11 -> 0 | D8: =IF(A8<=Supuestos!$B$19,Supuestos!$C$19,IF(A8<=Supuestos!$B$20,Supuestos!$C$20,IF(A8<=Supuestos!$B$21,Supuestos!$C$21,Supuestos!$C$21+(A8-Supuestos!$B$21)*Supuestos!$C$22))) -> 249 | E8: =D8*(1+Supuestos!$B$7)*(Supuestos!$B$8+Supuestos!$B$9)+Supuestos!$B$10 -> 6.2758 | F8: =D8-B8-C8-E8 -> 192.1242 | G8: =IF(D8=0,0,F8/D8) -> 0.77158313 | H8: =Supuestos!$C$26-B8-C8-(Supuestos!$C$26*(1+Supuestos!$B$7)*(Supuestos!$B$8+Supuestos!$B$9)+Supuestos!$B$10) -> -3.0358 | I8: =Supuestos!$C$27-B8-C8-(Supuestos!$C$27*(1+Supuestos!$B$7)*(Supuestos!$B$8+Supuestos!$B$9)+Supuestos!$B$10) -> 46.73 | J8: =A8*Supuestos!$B$13/60*Supuestos!$B$12 -> 450 | K8: =IF(J8=0,0,D8/J8) -> 0.55333333
A9: 1000 | B9: =A9*Supuestos!$B$5*Supuestos!$B$4*Supuestos!$B$6 -> 101.2 | C9: =A9*Supuestos!$B$11 -> 0 | D9: =IF(A9<=Supuestos!$B$19,Supuestos!$C$19,IF(A9<=Supuestos!$B$20,Supuestos!$C$20,IF(A9<=Supuestos!$B$21,Supuestos!$C$21,Supuestos!$C$21+(A9-Supuestos!$B$21)*Supuestos!$C$22))) -> 249 | E9: =D9*(1+Supuestos!$B$7)*(Supuestos!$B$8+Supuestos!$B$9)+Supuestos!$B$10 -> 6.2758 | F9: =D9-B9-C9-E9 -> 141.5242 | G9: =IF(D9=0,0,F9/D9) -> 0.56837028 | H9: =Supuestos!$C$26-B9-C9-(Supuestos!$C$26*(1+Supuestos!$B$7)*(Supuestos!$B$8+Supuestos!$B$9)+Supuestos!$B$10) -> -53.6358 | I9: =Supuestos!$C$27-B9-C9-(Supuestos!$C$27*(1+Supuestos!$B$7)*(Supuestos!$B$8+Supuestos!$B$9)+Supuestos!$B$10) -> -3.87 | J9: =A9*Supuestos!$B$13/60*Supuestos!$B$12 -> 900 | K9: =IF(J9=0,0,D9/J9) -> 0.27666667
A10: 2000 | B10: =A10*Supuestos!$B$5*Supuestos!$B$4*Supuestos!$B$6 -> 202.4 | C10: =A10*Supuestos!$B$11 -> 0 | D10: =IF(A10<=Supuestos!$B$19,Supuestos!$C$19,IF(A10<=Supuestos!$B$20,Supuestos!$C$20,IF(A10<=Supuestos!$B$21,Supuestos!$C$21,Supuestos!$C$21+(A10-Supuestos!$B$21)*Supuestos!$C$22))) -> 599 | E10: =D10*(1+Supuestos!$B$7)*(Supuestos!$B$8+Supuestos!$B$9)+Supuestos!$B$10 -> 14.7458 | F10: =D10-B10-C10-E10 -> 381.8542 | G10: =IF(D10=0,0,F10/D10) -> 0.63748614 | H10: =Supuestos!$C$26-B10-C10-(Supuestos!$C$26*(1+Supuestos!$B$7)*(Supuestos!$B$8+Supuestos!$B$9)+Supuestos!$B$10) -> -154.8358 | I10: =Supuestos!$C$27-B10-C10-(Supuestos!$C$27*(1+Supuestos!$B$7)*(Supuestos!$B$8+Supuestos!$B$9)+Supuestos!$B$10) -> -105.07 | J10: =A10*Supuestos!$B$13/60*Supuestos!$B$12 -> 1800 | K10: =IF(J10=0,0,D10/J10) -> 0.33277778
A11: 3000 | B11: =A11*Supuestos!$B$5*Supuestos!$B$4*Supuestos!$B$6 -> 303.6 | C11: =A11*Supuestos!$B$11 -> 0 | D11: =IF(A11<=Supuestos!$B$19,Supuestos!$C$19,IF(A11<=Supuestos!$B$20,Supuestos!$C$20,IF(A11<=Supuestos!$B$21,Supuestos!$C$21,Supuestos!$C$21+(A11-Supuestos!$B$21)*Supuestos!$C$22))) -> 599 | E11: =D11*(1+Supuestos!$B$7)*(Supuestos!$B$8+Supuestos!$B$9)+Supuestos!$B$10 -> 14.7458 | F11: =D11-B11-C11-E11 -> 280.6542 | G11: =IF(D11=0,0,F11/D11) -> 0.4685379 | H11: =Supuestos!$C$26-B11-C11-(Supuestos!$C$26*(1+Supuestos!$B$7)*(Supuestos!$B$8+Supuestos!$B$9)+Supuestos!$B$10) -> -256.0358 | I11: =Supuestos!$C$27-B11-C11-(Supuestos!$C$27*(1+Supuestos!$B$7)*(Supuestos!$B$8+Supuestos!$B$9)+Supuestos!$B$10) -> -206.27 | J11: =A11*Supuestos!$B$13/60*Supuestos!$B$12 -> 2700 | K11: =IF(J11=0,0,D11/J11) -> 0.22185185
A12: 5000 | B12: =A12*Supuestos!$B$5*Supuestos!$B$4*Supuestos!$B$6 -> 506 | C12: =A12*Supuestos!$B$11 -> 0 | D12: =IF(A12<=Supuestos!$B$19,Supuestos!$C$19,IF(A12<=Supuestos!$B$20,Supuestos!$C$20,IF(A12<=Supuestos!$B$21,Supuestos!$C$21,Supuestos!$C$21+(A12-Supuestos!$B$21)*Supuestos!$C$22))) -> 999 | E12: =D12*(1+Supuestos!$B$7)*(Supuestos!$B$8+Supuestos!$B$9)+Supuestos!$B$10 -> 24.4258 | F12: =D12-B12-C12-E12 -> 468.5742 | G12: =IF(D12=0,0,F12/D12) -> 0.46904324 | H12: =Supuestos!$C$26-B12-C12-(Supuestos!$C$26*(1+Supuestos!$B$7)*(Supuestos!$B$8+Supuestos!$B$9)+Supuestos!$B$10) -> -458.4358 | I12: =Supuestos!$C$27-B12-C12-(Supuestos!$C$27*(1+Supuestos!$B$7)*(Supuestos!$B$8+Supuestos!$B$9)+Supuestos!$B$10) -> -408.67 | J12: =A12*Supuestos!$B$13/60*Supuestos!$B$12 -> 4500 | K12: =IF(J12=0,0,D12/J12) -> 0.222
A14: Lectura: un margen negativo en 'plan fijo' significa que ese cliente le cuesta más de lo que paga.
A16: Con el precio de lanzamiento
A17: Facturas/mes | B17: Coste IA (€) | C17: WhatsApp (€) | D17: Precio lanzamiento (€) | E17: Stripe (€) | F17: Margen (€) | G17: Margen (%)
A18: 100 | B18: =A18*Supuestos!$B$5*Supuestos!$B$4*Supuestos!$B$6 -> 10.12 | C18: =A18*Supuestos!$B$11 -> 0 | D18: =Supuestos!$C$24 -> 29 | E18: =D18*(1+Supuestos!$B$7)*(Supuestos!$B$8+Supuestos!$B$9)+Supuestos!$B$10 -> 0.9518 | F18: =D18-B18-C18-E18 -> 17.9282 | G18: =IF(D18=0,0,F18/D18) -> 0.61821379
A19: 200 | B19: =A19*Supuestos!$B$5*Supuestos!$B$4*Supuestos!$B$6 -> 20.24 | C19: =A19*Supuestos!$B$11 -> 0 | D19: =Supuestos!$C$24 -> 29 | E19: =D19*(1+Supuestos!$B$7)*(Supuestos!$B$8+Supuestos!$B$9)+Supuestos!$B$10 -> 0.9518 | F19: =D19-B19-C19-E19 -> 7.8082 | G19: =IF(D19=0,0,F19/D19) -> 0.26924828
A20: 500 | B20: =A20*Supuestos!$B$5*Supuestos!$B$4*Supuestos!$B$6 -> 50.6 | C20: =A20*Supuestos!$B$11 -> 0 | D20: =Supuestos!$C$24 -> 29 | E20: =D20*(1+Supuestos!$B$7)*(Supuestos!$B$8+Supuestos!$B$9)+Supuestos!$B$10 -> 0.9518 | F20: =D20-B20-C20-E20 -> -22.5518 | G20: =IF(D20=0,0,F20/D20) -> -0.77764828
A21: 1000 | B21: =A21*Supuestos!$B$5*Supuestos!$B$4*Supuestos!$B$6 -> 101.2 | C21: =A21*Supuestos!$B$11 -> 0 | D21: =Supuestos!$C$24 -> 29 | E21: =D21*(1+Supuestos!$B$7)*(Supuestos!$B$8+Supuestos!$B$9)+Supuestos!$B$10 -> 0.9518 | F21: =D21-B21-C21-E21 -> -73.1518 | G21: =IF(D21=0,0,F21/D21) -> -2.5224759
A22: Con el límite de la promoción (hoja Supuestos, B24), el cliente nunca cuesta más de lo que paga si el margen de su fila es positivo.

Sheet Equilibrio
A1: Cuántos clientes hacen falta
A3: Concepto | B3: Valor | C3: Nota
A4: Facturas al mes del cliente típico | B4: =Supuestos!B14 -> 200 | C4: Se cambia en Supuestos.
A5: Precio del tramo que le corresponde (€, sin IVA) | B5: =IF(B4<=Supuestos!B19,Supuestos!C19,IF(B4<=Supuestos!B20,Supuestos!C20,IF(B4<=Supuestos!B21,Supuestos!C21,Supuestos!C21+(B4-Supuestos!B21)*Supuestos!C22))) -> 49
A6: Costes variables por cliente (€) | B6: =B4*Supuestos!B5*Supuestos!B4*Supuestos!B6+B4*Supuestos!B11+B5*(1+Supuestos!B7)*(Supuestos!B8+Supuestos!B9)+Supuestos!B10 -> 21.6758 | C6: IA + WhatsApp + Stripe.
A7: Margen por cliente a precio habitual (€/mes) | B7: =B5-B6 -> 27.3242
A8: Margen por cliente a precio de lanzamiento (€/mes) | B8: =Supuestos!C24-(B4*Supuestos!B5*Supuestos!B4*Supuestos!B6+B4*Supuestos!B11+Supuestos!C24*(1+Supuestos!B7)*(Supuestos!B8+Supuestos!B9)+Supuestos!B10) -> 7.8082 | C8: Válido si el cliente cabe en el límite de la promoción.
A9: Costes fijos de producción (€/mes) | B9: =Fijos!C9 -> 30.273333 | C9: De la hoja Fijos.
A10: Clientes para cubrir los costes fijos (precio habitual) | B10: =IF(B7<=0,"no se cubre",ROUNDUP(B9/B7,0)) -> 2
A11: Clientes para cubrir los costes fijos (lanzamiento) | B11: =IF(B8<=0,"no se cubre",ROUNDUP(B9/B8,0)) -> 4
A12: Objetivo de ingresos netos (€/mes) | B12: =Supuestos!B15 -> 2000
A13: Clientes para el objetivo (precio habitual) | B13: =IF(B7<=0,"no se cubre",ROUNDUP((B12+B9)/B7,0)) -> 75 | C13: Antes de impuestos y cuota de autónomos.
A14: Clientes para el objetivo (lanzamiento) | B14: =IF(B8<=0,"no se cubre",ROUNDUP((B12+B9)/B8,0)) -> 261
A15: Coste fijo de arrancar con la gestoría de prueba (€/mes) | B15: =Fijos!D9 -> 0.83333333 | C15: Lo que cuesta hoy el piloto.

Sheet Notas
A1: Notas, fuentes y qué no incluye
A3: Fuentes de precios (consultadas en octubre de 2026; confirmar antes de decidir):
A4: · IA: Claude Sonnet 5.5 a 2 $ por millón de tokens de entrada y 10 $ de salida (apidog.com y anotherwrapper.com; confirmar en la consola de Anthropic).
A5: · Servidor: render.com/pricing (plan de 7 $/mes; el gratuito se duerme).
A6: · Base de datos: supabase.com/docs/pricing (Pro desde 25 $/mes, copias diarias 7 días).
A7: · Correo: Resend, gratis hasta 3.000 correos/mes (automationatlas.io).
A8: · Stripe: 1,5 % + 0,25 € por cobro con tarjeta europea y 0,5 % extra por suscripciones (getquipu.com/blog/comisiones-stripe).
A10: Lo que NO incluye este modelo:
A11: · Impuestos, IVA ingresado y cuota de autónomos o de sociedad.
A12: · Su tiempo de soporte y desarrollo.
A13: · Revisión legal de los textos (puntual) y verificaciones de Google y Microsoft.
A14: · Meta/WhatsApp: está a 0 hasta que se active el servicio y se conozca la tarifa.
... A17: Los supuestos en amarillo (coste de IA por factura, minutos a mano, facturas del cliente típico) son los que más cambian el resultado.

Sheet Optimizacion
A1: Ahorro con el modelo barato de IA (primera lectura barata, el principal solo si hay dudas)
A2: Los dos supuestos en amarillo se sustituyen por datos reales con /admin/uso-ia (comparación de modelos).
A3: Supuesto | B3: Valor | C3: Nota
A4: Precio del modelo barato respecto al principal | B4: 0.05 | C4: Haiku 5.5: 0,10 $ / 0,50 $ por millón de tokens frente a 2 $ / 10 $ de Sonnet 5.5 (≈5 %). Fuentes: apidog.com (confirmar en la consola de Anthropic). Supone que cuesta igual leer un PDF con uno que con otro.
A5: Lecturas que acaban pasando al modelo principal | B5: 0.25 | C5: Supuesto: el 25 % sale dudoso o no cuadra y se repite con Sonnet. Medirlo con el contador.
A6: Descuento por proceso en lote (Batch API) | B6: 0 | C6: 0 % = no se usa. Según las fuentes, el lote cuesta la mitad (50 %), pero no es inmediato.
A8: Coste de IA por factura (€)
A9: Solo modelo principal | B9: =Supuestos!B4*Supuestos!B5*Supuestos!B6 -> 0.1012
A10: Con modelo barato primero | B10: =B9*(B4+B5)*(1-B6) -> 0.03036
A11: Ahorro por factura | B11: =IF(B9=0,0,1-B10/B9) -> 0.7
A13: Facturas/mes | B13: Coste IA solo principal (€) | C13: Coste IA con modelo barato (€) | D13: Ahorro al mes (€) | E13: Precio del tramo (€) | F13: Margen tramo, solo principal (%) | G13: Margen tramo, con modelo barato (%)
A14: 100 | B14: =A14*$B$9 -> 10.12 | C14: =A14*$B$10 -> 3.036 | D14: =B14-C14 -> 7.084 | E14: =IF(A14<=Supuestos!$B$19,Supuestos!$C$19,IF(A14<=Supuestos!$B$20,Supuestos!$C$20,IF(A14<=Supuestos!$B$21,Supuestos!$C$21,Supuestos!$C$21+(A14-Supuestos!$B$21)*Supuestos!$C$22))) -> 49 | F14: =IF(E14=0,0,(E14-B14-(E14*(1+Supuestos!$B$7)*(Supuestos!$B$8+Supuestos!$B$9)+Supuestos!$B$10))/E14) -> 0.76416735 | G14: =IF(E14=0,0,(E14-C14-(E14*(1+Supuestos!$B$7)*(Supuestos!$B$8+Supuestos!$B$9)+Supuestos!$B$10))/E14) -> 0.90873878
A15: 200 | B15: =A15*$B$9 -> 20.24 | C15: =A15*$B$10 -> 6.072 | D15: =B15-C15 -> 14.168 | E15: =IF(A15<=Supuestos!$B$19,Supuestos!$C$19,IF(A15<=Supuestos!$B$20,Supuestos!$C$20,IF(A15<=Supuestos!$B$21,Supuestos!$C$21,Supuestos!$C$21+(A15-Supuestos!$B$21)*Supuestos!$C$22))) -> 49 | F15: =IF(E15=0,0,(E15-B15-(E15*(1+Supuestos!$B$7)*(Supuestos!$B$8+Supuestos!$B$9)+Supuestos!$B$10))/E15) -> 0.55763673 | G15: =IF(E15=0,0,(E15-C15-(E15*(1+Supuestos!$B$7)*(Supuestos!$B$8+Supuestos!$B$9)+Supuestos!$B$10))/E15) -> 0.84677959
A16: 500 | B16: =A16*$B$9 -> 50.6 | C16: =A16*$B$10 -> 15.18 | D16: =B16-C16 -> 35.42 | E16: =IF(A16<=Supuestos!$B$19,Supuestos!$C$19,IF(A16<=Supuestos!$B$20,Supuestos!$C$20,IF(A16<=Supuestos!$B$21,Supuestos!$C$21,Supuestos!$C$21+(A16-Supuestos!$B$21)*Supuestos!$C$22))) -> 249 | F16: =IF(E16=0,0,(E16-B16-(E16*(1+Supuestos!$B$7)*(Supuestos!$B$8+Supuestos!$B$9)+Supuestos!$B$10))/E16) -> 0.77158313 | G16: =IF(E16=0,0,(E16-C16-(E16*(1+Supuestos!$B$7)*(Supuestos!$B$8+Supuestos!$B$9)+Supuestos!$B$10))/E16) -> 0.91383213
A17: 1000 | B17: =A17*$B$9 -> 101.2 | C17: =A17*$B$10 -> 30.36 | D17: =B17-C17 -> 70.84 | E17: =IF(A17<=Supuestos!$B$19,Supuestos!$C$19,IF(A17<=Supuestos!$B$20,Supuestos!$C$20,IF(A17<=Supuestos!$B$21,Supuestos!$C$21,Supuestos!$C$21+(A17-Supuestos!$B$21)*Supuestos!$C$22))) -> 249 | F17: =IF(E17=0,0,(E17-B17-(E17*(1+Supuestos!$B$7)*(Supuestos!$B$8+Supuestos!$B$9)+Supuestos!$B$10))/E17) -> 0.56837028 | G17: =IF(E17=0,0,(E17-C17-(E17*(1+Supuestos!$B$7)*(Supuestos!$B$8+Supuestos!$B$9)+Supuestos!$B$10))/E17) -> 0.85286827
A18: 2000 | B18: =A18*$B$9 -> 202.4 | C18: =A18*$B$10 -> 60.72 | D18: =B18-C18 -> 141.68 | E18: =IF(A18<=Supuestos!$B$19,Supuestos!$C$19,IF(A18<=Supuestos!$B$20,Supuestos!$C$20,IF(A18<=Supuestos!$B$21,Supuestos!$C$21,Supuestos!$C$21+(A18-Supuestos!$B$21)*Supuestos!$C$22))) -> 599 | F18: =IF(E18=0,0,(E18-B18-(E18*(1+Supuestos!$B$7)*(Supuestos!$B$8+Supuestos!$B$9)+Supuestos!$B$10))/E18) -> 0.63748614 | G18: =IF(E18=0,0,(E18-C18-(E18*(1+Supuestos!$B$7)*(Supuestos!$B$8+Supuestos!$B$9)+Supuestos!$B$10))/E18) -> 0.87401369
A19: 3000 | B19: =A19*$B$9 -> 303.6 | C19: =A19*$B$10 -> 91.08 | D19: =B19-C19 -> 212.52 | E19: =IF(A19<=Supuestos!$B$19,Supuestos!$C$19,IF(A19<=Supuestos!$B$20,Supuestos!$C$20,IF(A19<=Supuestos!$B$21,Supuestos!$C$21,Supuestos!$C$21+(A19-Supuestos!$B$21)*Supuestos!$C$22))) -> 599 | F19: =IF(E19=0,0,(E19-B19-(E19*(1+Supuestos!$B$7)*(Supuestos!$B$8+Supuestos!$B$9)+Supuestos!$B$10))/E19) -> 0.4685379 | G19: =IF(E19=0,0,(E19-C19-(E19*(1+Supuestos!$B$7)*(Supuestos!$B$8+Supuestos!$B$9)+Supuestos!$B$10))/E19) -> 0.82332922
A20: 5000 | B20: =A20*$B$9 -> 506 | C20: =A20*$B$10 -> 151.8 | D20: =B20-C20 -> 354.2 | E20: =IF(A20<=Supuestos!$B$19,Supuestos!$C$19,IF(A20<=Supuestos!$B$20,Supuestos!$C$20,IF(A20<=Supuestos!$B$21,Supuestos!$C$21,Supuestos!$C$21+(A20-Supuestos!$B$21)*Supuestos!$C$22))) -> 999 | F20: =IF(E20=0,0,(E20-B20-(E20*(1+Supuestos!$B$7)*(Supuestos!$B$8+Supuestos!$B$9)+Supuestos!$B$10))/E20) -> 0.46904324 | G20: =IF(E20=0,0,(E20-C20-(E20*(1+Supuestos!$B$7)*(Supuestos!$B$8+Supuestos!$B$9)+Supuestos!$B$10))/E20) -> 0.8235978
A22: Con un coste de IA tan bajo, los tramos de precio pueden ser más baratos o el margen mucho mayor: decidir con datos reales.
